elective/__init__.py
elective/config.py
elective-0.1.1.dist-info/LICENSE.rst
elective-0.1.1.dist-info/METADATA
elective-0.1.1.dist-info/WHEEL
elective-0.1.1.dist-info/entry_points.txt
elective-0.1.1.dist-info/top_level.txt
elective-0.1.1.dist-info/RECORD
