Metadata-Version: 2.1
Name: elective
Version: 0.1.1
Summary: python program configuration option loader
Home-page: https://github.com/jeremyagray/elective
Author: Jeremy A Gray
Author-email: jeremy.a.gray@gmail.com
Maintainer: Jeremy A Gray
Maintainer-email: jeremy.a.gray@gmail.com
License: GPL-3.0-or-later
Project-URL: Issues, https://github.com/jeremyagray/elective/issues
Project-URL: Documentation, https://elective.readthedocs.io/
Project-URL: Repository, https://github.com/jeremyagray/elective
Platform: UNKNOWN
Classifier: Development Status :: 1 - Planning
Classifier: Environment :: Console
Classifier: License :: OSI Approved :: GNU General Public License v3 or later (GPLv3+)
Classifier: Intended Audience :: Developers
Classifier: Programming Language :: Python :: 3.6
Classifier: Programming Language :: Python :: 3.7
Classifier: Programming Language :: Python :: 3.8
Classifier: Programming Language :: Python :: 3.9
Classifier: Topic :: Software Development :: User Interfaces
Requires-Dist: toml
